uestc_login/__init__.py
uestc_login/exceptions.py
uestc_login/login.py
uestc_login/utils.py
uestc_login-0.1.5.dist-info/licenses/LICENSE
uestc_login-0.1.5.dist-info/METADATA
uestc_login-0.1.5.dist-info/WHEEL
uestc_login-0.1.5.dist-info/top_level.txt
uestc_login-0.1.5.dist-info/RECORD
