Metadata-Version: 2.4
Name: uestc-login
Version: 0.1.5
Summary: A login utility for UESTC services (IDAS, Mooc, etc.)
Author-email: H3CoF6 <h3cof6@gmail.com>
Project-URL: Homepage, https://github.com/H3CoF6/uestc-login
Project-URL: Bug Tracker, https://github.com/H3CoF6/uestc-login/issues
Classifier: Programming Language :: Python :: 3
Classifier: License :: OSI Approved :: MIT License
Classifier: Operating System :: OS Independent
Requires-Python: >=3.7
License-File: LICENSE
Requires-Dist: requests
Requires-Dist: beautifulsoup4
Requires-Dist: pycryptodome
Dynamic: license-file
